{
  "type": "Feature",
  "properties": {
    "gn:admin1_code":"6.0",
    "gn:asciiname":"New Haven",
    "gn:country_code":"BZ",
    "gn:dem":-9999,
    "gn:feature_class":"P",
    "gn:feature_code":"PPL",
    "gn:name":"New Haven",
    "gn:population":0,
    "gn:timezone":"America/Belize",
    "iso:country":"BZ",
    "wof:name":"New Haven",
    "wof:placetype":"locality"
},
  "geometry": {"coordinates":[-88.59054,16.25418],"type":"Point"}
}