{
  "type": "Feature",
  "properties": {
    "gn:admin1_code":"4.0",
    "gn:asciiname":"San Felipe",
    "gn:country_code":"BZ",
    "gn:dem":28,
    "gn:feature_class":"P",
    "gn:feature_code":"PPL",
    "gn:name":"San Felipe",
    "gn:population":0,
    "gn:timezone":"America/Belize",
    "iso:country":"BZ",
    "name:spa_x_preferred":[
        "San Felipe"
    ],
    "wof:name":"San Felipe",
    "wof:placetype":"locality"
},
  "geometry": {"coordinates":[-88.77334,17.873],"type":"Point"}
}