{
  "type": "Feature",
  "properties": {
    "gn:admin1_code":"2.0",
    "gn:asciiname":"Spanish Lookout",
    "gn:country_code":"BZ",
    "gn:dem":105,
    "gn:feature_class":"P",
    "gn:feature_code":"PPL",
    "gn:name":"Spanish Lookout",
    "gn:population":0,
    "gn:timezone":"America/Belize",
    "iso:country":"BZ",
    "wof:name":"Spanish Lookout",
    "wof:placetype":"locality"
},
  "geometry": {"coordinates":[-89.00917,17.26278],"type":"Point"}
}