{
  "type": "Feature",
  "properties": {
    "gn:admin1_code":"2.0",
    "gn:asciiname":"Baldy Beacon",
    "gn:country_code":"BZ",
    "gn:dem":970,
    "gn:feature_class":"P",
    "gn:feature_code":"PPL",
    "gn:name":"Baldy Beacon",
    "gn:population":0,
    "gn:timezone":"America/Belize",
    "iso:country":"BZ",
    "name:und_x_variant":[
        "Baldy Ben",
        "Baldy Beacon"
    ],
    "wof:name":"Baldy Beacon",
    "wof:placetype":"locality"
},
  "geometry": {"coordinates":[-88.79174,17.00347],"type":"Point"}
}