{
  "type": "Feature",
  "properties": {
    "gn:admin1_code":"2.0",
    "gn:asciiname":"St. Margaret",
    "gn:country_code":"BZ",
    "gn:dem":104,
    "gn:feature_class":"P",
    "gn:feature_code":"PPL",
    "gn:name":"St. Margaret",
    "gn:population":0,
    "gn:timezone":"America/Belize",
    "iso:country":"BZ",
    "name:nds_x_preferred":[
        "Santa Martha"
    ],
    "wof:name":"St. Margaret",
    "wof:placetype":"locality"
},
  "geometry": {"coordinates":[-88.61095999999998,17.09047],"type":"Point"}
}