{
  "type": "Feature",
  "properties": {
    "iso:country":"BZ",
    "qs:gn_country":"BZ",
    "qs:gn_fcode":"PPL",
    "qs:gn_pop":0,
    "qs:name":"San Antonio",
    "qs:name_adm0":"Belize",
    "qs:name_adm1":"Toledo",
    "qs:photos":145,
    "qs:photos_1k":29,
    "qs:photos_9k":1,
    "qs:photos_9r":3,
    "qs:photos_all":145,
    "qs:photos_sr":3,
    "qs:placetype":"Town",
    "qs:pop_sr":"0",
    "qs:woe_adm0":23424760,
    "wof:name":"San Antonio",
    "wof:placetype":"locality"
},
  "geometry": {"coordinates":[-89.02417,16.24361],"type":"Point"}
}