{
  "type": "Feature",
  "properties": {
    "gn:admin1_code":"6.0",
    "gn:asciiname":"Machaca Camp",
    "gn:country_code":"BZ",
    "gn:dem":33,
    "gn:feature_class":"P",
    "gn:feature_code":"PPL",
    "gn:name":"Machaca Camp",
    "gn:population":0,
    "gn:timezone":"America/Belize",
    "iso:country":"BZ",
    "wof:name":"Machaca Camp",
    "wof:placetype":"locality"
},
  "geometry": {"coordinates":[-88.88854000000001,16.19903],"type":"Point"}
}