{
  "type": "Feature",
  "properties": {
    "gn:admin1_code":"2.0",
    "gn:asciiname":"Branch Mouth",
    "gn:country_code":"BZ",
    "gn:dem":57,
    "gn:feature_class":"P",
    "gn:feature_code":"PPL",
    "gn:name":"Branch Mouth",
    "gn:population":0,
    "gn:timezone":"America/Belize",
    "iso:country":"BZ",
    "name:eng_x_preferred":[
        "Branch Mouth"
    ],
    "wof:name":"Branch Mouth",
    "wof:placetype":"locality"
},
  "geometry": {"coordinates":[-89.07973,17.17939],"type":"Point"}
}