{
  "type": "Feature",
  "properties": {
    "gn:admin1_code":"2.0",
    "gn:asciiname":"Buena Vista",
    "gn:country_code":"BZ",
    "gn:dem":97,
    "gn:feature_class":"P",
    "gn:feature_code":"PPL",
    "gn:name":"Buena Vista",
    "gn:population":0,
    "gn:timezone":"America/Belize",
    "iso:country":"BZ",
    "name:spa_x_preferred":[
        "Buena Vista"
    ],
    "wof:name":"Buena Vista",
    "wof:placetype":"locality"
},
  "geometry": {"coordinates":[-89.11667,17.11667000000001],"type":"Point"}
}