{
  "type": "Feature",
  "properties": {
    "gn:admin1_code":"6.0",
    "gn:asciiname":"Perry Bank",
    "gn:country_code":"BZ",
    "gn:dem":52,
    "gn:feature_class":"P",
    "gn:feature_code":"PPL",
    "gn:name":"Perry Bank",
    "gn:population":0,
    "gn:timezone":"America/Belize",
    "iso:country":"BZ",
    "wof:name":"Perry Bank",
    "wof:placetype":"locality"
},
  "geometry": {"coordinates":[-88.57666999999999,16.6098],"type":"Point"}
}