{
  "type": "Feature",
  "properties": {
    "gn:admin1_code":"5.0",
    "gn:asciiname":"Red Bank",
    "gn:country_code":"BZ",
    "gn:dem":89,
    "gn:feature_class":"P",
    "gn:feature_code":"PPL",
    "gn:name":"Red Bank",
    "gn:population":0,
    "gn:timezone":"America/Belize",
    "iso:country":"BZ",
    "name:cat_x_preferred":[
        "Red Bank"
    ],
    "name:ceb_x_preferred":[
        "Red Bank"
    ],
    "name:deu_x_preferred":[
        "Red Bank"
    ],
    "name:fra_x_preferred":[
        "Red Bank"
    ],
    "name:ita_x_preferred":[
        "Red Bank"
    ],
    "name:nds_x_preferred":[
        "Red Bank"
    ],
    "name:nld_x_preferred":[
        "Red Bank"
    ],
    "name:pol_x_preferred":[
        "Red Bank"
    ],
    "name:por_x_preferred":[
        "Red Bank"
    ],
    "name:srp_x_preferred":[
        "\u0420\u0435\u0434 \u0411\u0430\u043d\u043a"
    ],
    "name:swe_x_preferred":[
        "Red Bank"
    ],
    "name:vol_x_preferred":[
        "Red Bank"
    ],
    "wof:name":"Red Bank",
    "wof:placetype":"locality"
},
  "geometry": {"coordinates":[-88.49271,16.76304],"type":"Point"}
}