{
  "type": "Feature",
  "properties": {
    "gn:admin1_code":"2.0",
    "gn:asciiname":"Cebada Camp",
    "gn:country_code":"BZ",
    "gn:dem":562,
    "gn:feature_class":"P",
    "gn:feature_code":"PPL",
    "gn:name":"Cebada Camp",
    "gn:population":0,
    "gn:timezone":"America/Belize",
    "iso:country":"BZ",
    "wof:name":"Cebada Camp",
    "wof:placetype":"locality"
},
  "geometry": {"coordinates":[-89.16424000000001,16.65712000000001],"type":"Point"}
}