{
  "type": "Feature",
  "properties": {
    "gn:admin1_code":"2.0",
    "gn:asciiname":"Ontario Village",
    "gn:country_code":"BZ",
    "gn:dem":84,
    "gn:feature_class":"P",
    "gn:feature_code":"PPL",
    "gn:name":"Ontario Village",
    "gn:population":0,
    "gn:timezone":"America/Belize",
    "iso:country":"BZ",
    "wof:name":"Ontario Village",
    "wof:placetype":"locality"
},
  "geometry": {"coordinates":[-88.89189,17.22121],"type":"Point"}
}