{
  "type": "Feature",
  "properties": {
    "gn:admin1_code":"6.0",
    "gn:asciiname":"Piebra",
    "gn:country_code":"BZ",
    "gn:dem":8,
    "gn:feature_class":"P",
    "gn:feature_code":"PPL",
    "gn:name":"Piebra",
    "gn:population":0,
    "gn:timezone":"America/Belize",
    "iso:country":"BZ",
    "wof:name":"Piebra",
    "wof:placetype":"locality"
},
  "geometry": {"coordinates":[-88.93915,16.10434],"type":"Point"}
}