{
  "type": "Feature",
  "properties": {
    "gn:admin1_code":"2.0",
    "gn:asciiname":"Augustine",
    "gn:country_code":"BZ",
    "gn:dem":455,
    "gn:feature_class":"P",
    "gn:feature_code":"PPL",
    "gn:name":"Augustine",
    "gn:population":0,
    "gn:timezone":"America/Belize",
    "iso:country":"BZ",
    "wof:name":"Augustine",
    "wof:placetype":"locality"
},
  "geometry": {"coordinates":[-88.99718,16.96712],"type":"Point"}
}