{
  "type": "Feature",
  "properties": {
    "gn:admin1_code":"5.0",
    "gn:asciiname":"Sale si Puede",
    "gn:country_code":"BZ",
    "gn:dem":164,
    "gn:feature_class":"P",
    "gn:feature_code":"PPL",
    "gn:name":"Sale si Puede",
    "gn:population":0,
    "gn:timezone":"America/Belize",
    "iso:country":"BZ",
    "wof:name":"Sale si Puede",
    "wof:placetype":"locality"
},
  "geometry": {"coordinates":[-88.63606,16.71334],"type":"Point"}
}