{
  "type": "Feature",
  "properties": {
    "gn:admin1_code":"4.0",
    "gn:asciiname":"Honey Camp",
    "gn:country_code":"BZ",
    "gn:dem":16,
    "gn:feature_class":"P",
    "gn:feature_code":"PPL",
    "gn:name":"Honey Camp",
    "gn:population":0,
    "gn:timezone":"America/Belize",
    "iso:country":"BZ",
    "wof:name":"Honey Camp",
    "wof:placetype":"locality"
},
  "geometry": {"coordinates":[-88.45013,18.0327],"type":"Point"}
}