{
  "type": "Feature",
  "properties": {
    "gn:admin1_code":"3.0",
    "gn:asciiname":"Cocos",
    "gn:country_code":"BZ",
    "gn:dem":18,
    "gn:feature_class":"P",
    "gn:feature_code":"PPL",
    "gn:name":"Cocos",
    "gn:population":0,
    "gn:timezone":"America/Belize",
    "iso:country":"BZ",
    "wof:name":"Cocos",
    "wof:placetype":"locality"
},
  "geometry": {"coordinates":[-88.37340999999998,18.25141],"type":"Point"}
}