{
  "type": "Feature",
  "properties": {
    "gn:admin1_code":"2.0",
    "gn:asciiname":"Duck Run",
    "gn:country_code":"BZ",
    "gn:dem":54,
    "gn:feature_class":"P",
    "gn:feature_code":"PPL",
    "gn:name":"Duck Run",
    "gn:population":0,
    "gn:timezone":"America/Belize",
    "iso:country":"BZ",
    "name:eng_x_preferred":[
        "Duck Run"
    ],
    "wof:name":"Duck Run",
    "wof:placetype":"locality"
},
  "geometry": {"coordinates":[-89.04821,17.18482],"type":"Point"}
}