{
  "type": "Feature",
  "properties": {
    "gn:admin1_code":"2.0",
    "gn:asciiname":"Teakettle Village",
    "gn:country_code":"BZ",
    "gn:dem":51,
    "gn:feature_class":"P",
    "gn:feature_code":"PPL",
    "gn:name":"Teakettle Village",
    "gn:population":0,
    "gn:timezone":"America/Belize",
    "iso:country":"BZ",
    "name:und_x_variant":[
        "Teakettle",
        "Teakettle Bank",
        "Teakettle Village"
    ],
    "wof:name":"Teakettle Village",
    "wof:placetype":"locality"
},
  "geometry": {"coordinates":[-88.85499,17.2295],"type":"Point"}
}