{
  "type": "Feature",
  "properties": {
    "gn:admin1_code":"4.0",
    "gn:asciiname":"Rejolla",
    "gn:country_code":"BZ",
    "gn:dem":203,
    "gn:feature_class":"P",
    "gn:feature_code":"PPL",
    "gn:name":"Rejolla",
    "gn:population":0,
    "gn:timezone":"America/Belize",
    "iso:country":"BZ",
    "wof:name":"Rejolla",
    "wof:placetype":"locality"
},
  "geometry": {"coordinates":[-89.12130999999999,17.41947],"type":"Point"}
}