{
  "type": "Feature",
  "properties": {
    "gn:admin1_code":"4.0",
    "gn:asciiname":"Esperanza",
    "gn:country_code":"BZ",
    "gn:dem":157,
    "gn:feature_class":"P",
    "gn:feature_code":"PPL",
    "gn:name":"Esperanza",
    "gn:population":0,
    "gn:timezone":"America/Belize",
    "iso:country":"BZ",
    "name:spa_x_preferred":[
        "Esperanza"
    ],
    "wof:name":"Esperanza",
    "wof:placetype":"locality"
},
  "geometry": {"coordinates":[-89.13084000000001,17.37796],"type":"Point"}
}