{
  "type": "Feature",
  "properties": {
    "gn:admin1_code":"4.0",
    "gn:asciiname":"Esperanza",
    "gn:country_code":"BZ",
    "gn:dem":157,
    "gn:feature_class":"P",
    "gn:feature_code":"PPL",
    "gn:name":"Esperanza",
    "gn:population":0,
    "gn:timezone":"America/Belize",
    "iso:country":"BZ",
    "name:bre_x_preferred":[
        "Esperanza"
    ],
    "name:ceb_x_preferred":[
        "Esperanza"
    ],
    "name:deu_x_preferred":[
        "Esperanza"
    ],
    "name:epo_x_preferred":[
        "Esperanza"
    ],
    "name:fra_x_preferred":[
        "Esperanza"
    ],
    "name:glg_x_preferred":[
        "Esperanza"
    ],
    "name:hye_x_preferred":[
        "\u0537\u057d\u057a\u0565\u0580\u0561\u0576\u057d\u0561"
    ],
    "name:ita_x_preferred":[
        "Esperanza"
    ],
    "name:jpn_x_preferred":[
        "\u30a8\u30b9\u30da\u30e9\u30f3\u30b5"
    ],
    "name:kor_x_preferred":[
        "\uc5d0\uc2a4\ud398\ub780\uc790"
    ],
    "name:kor_x_variant":[
        "\uc5d0\uc2a4\ud398\ub780\uc0ac"
    ],
    "name:nds_x_preferred":[
        "Esperanza"
    ],
    "name:nld_x_preferred":[
        "Esperanza"
    ],
    "name:por_x_preferred":[
        "Esperanza"
    ],
    "name:rus_x_preferred":[
        "\u042d\u0441\u043f\u0435\u0440\u0430\u043d\u0441\u0430"
    ],
    "name:spa_x_preferred":[
        "Esperanza"
    ],
    "name:srp_x_preferred":[
        "\u0415\u0441\u043f\u0435\u0440\u0430\u043d\u0437\u0430"
    ],
    "name:swe_x_preferred":[
        "Esperanza"
    ],
    "name:tgl_x_preferred":[
        "Esperanza"
    ],
    "name:tur_x_preferred":[
        "Esperanza"
    ],
    "name:ukr_x_preferred":[
        "\u0415\u0441\u043f\u0435\u0440\u0430\u043d\u0441\u0430"
    ],
    "name:urd_x_preferred":[
        "\u0627\u06cc\u0633\u067e\u06cc\u0631\u06cc\u0646\u0632\u0627"
    ],
    "name:vie_x_preferred":[
        "Esperanza"
    ],
    "name:war_x_preferred":[
        "Esperanza"
    ],
    "name:zho_cn_x_preferred":[
        "\u57c3\u65af\u4f69\u5170\u8428"
    ],
    "name:zho_tw_x_preferred":[
        "\u57c3\u65af\u4f69\u862d\u85a9"
    ],
    "wof:name":"Esperanza",
    "wof:placetype":"locality"
},
  "geometry": {"coordinates":[-89.13084000000001,17.37796],"type":"Point"}
}