{
  "type": "Feature",
  "properties": {
    "gn:admin1_code":"3.0",
    "gn:asciiname":"Chacan Chac Mol",
    "gn:country_code":"BZ",
    "gn:dem":13,
    "gn:feature_class":"P",
    "gn:feature_code":"PPL",
    "gn:name":"Chacan Chac Mol",
    "gn:population":0,
    "gn:timezone":"America/Belize",
    "iso:country":"BZ",
    "name:und_x_variant":[
        "Chakan Chak Mol",
        "Chacan Chac Mol"
    ],
    "wof:name":"Chacan Chac Mol",
    "wof:placetype":"locality"
},
  "geometry": {"coordinates":[-88.25743,18.27377000000001],"type":"Point"}
}