{
  "type": "Feature",
  "properties": {
    "gn:admin1_code":"3.0",
    "gn:asciiname":"Progresso",
    "gn:country_code":"BZ",
    "gn:dem":8,
    "gn:feature_class":"P",
    "gn:feature_code":"PPL",
    "gn:name":"Progresso",
    "gn:population":0,
    "gn:timezone":"America/Belize",
    "iso:country":"BZ",
    "name:ceb_x_preferred":[
        "Progresso"
    ],
    "name:deu_x_preferred":[
        "Progresso"
    ],
    "name:nds_x_preferred":[
        "Progresso"
    ],
    "name:pol_x_preferred":[
        "Progresso"
    ],
    "name:por_x_preferred":[
        "Progresso"
    ],
    "name:spa_x_preferred":[
        "Progreso"
    ],
    "name:swe_x_preferred":[
        "Progresso"
    ],
    "wof:name":"Progresso",
    "wof:placetype":"locality"
},
  "geometry": {"coordinates":[-88.41073,18.23085],"type":"Point"}
}