{
  "type": "Feature",
  "properties": {
    "gn:admin1_code":"3.0",
    "gn:asciiname":"Progresso",
    "gn:country_code":"BZ",
    "gn:dem":8,
    "gn:feature_class":"P",
    "gn:feature_code":"PPL",
    "gn:name":"Progresso",
    "gn:population":0,
    "gn:timezone":"America/Belize",
    "iso:country":"BZ",
    "name:und_x_variant":[
        "Progreso",
        "Progresso"
    ],
    "wof:name":"Progresso",
    "wof:placetype":"locality"
},
  "geometry": {"coordinates":[-88.41073,18.23085],"type":"Point"}
}