{
  "type": "Feature",
  "properties": {
    "gn:admin1_code":"4.0",
    "gn:asciiname":"Tres Leguas Mennonite Settlement",
    "gn:country_code":"BZ",
    "gn:dem":139,
    "gn:feature_class":"P",
    "gn:feature_code":"PPLR",
    "gn:name":"Tres Leguas Mennonite Settlement",
    "gn:population":0,
    "gn:timezone":"America/Belize",
    "iso:country":"BZ",
    "name:und_x_variant":[
        "Tres Leguas Menonite Settlement",
        "Tres Leguas Mennonite Settlement"
    ],
    "wof:name":"Tres Leguas Mennonite Settlement",
    "wof:placetype":"locality"
},
  "geometry": {"coordinates":[-88.91699,17.88432000000001],"type":"Point"}
}