{
  "type": "Feature",
  "properties": {
    "gn:admin1_code":"6.0",
    "gn:asciiname":"Logan's Bank",
    "gn:country_code":"BZ",
    "gn:dem":37,
    "gn:feature_class":"P",
    "gn:feature_code":"PPL",
    "gn:name":"Logan\u2019s Bank",
    "gn:population":0,
    "gn:timezone":"America/Belize",
    "iso:country":"BZ",
    "wof:name":"Logan's Bank",
    "wof:placetype":"locality"
},
  "geometry": {"coordinates":[-88.54279,16.48943],"type":"Point"}
}