{
  "type": "Feature",
  "properties": {
    "gn:admin1_code":"3.0",
    "gn:asciiname":"Swasey Branch Barquedier",
    "gn:country_code":"BZ",
    "gn:dem":13,
    "gn:feature_class":"P",
    "gn:feature_code":"PPL",
    "gn:name":"Swasey Branch Barquedier",
    "gn:population":0,
    "gn:timezone":"America/Belize",
    "iso:country":"BZ",
    "wof:name":"Swasey Branch Barquedier",
    "wof:placetype":"locality"
},
  "geometry": {"coordinates":[-88.47169,18.1876],"type":"Point"}
}