{
  "type": "Feature",
  "properties": {
    "gn:admin1_code":"4.0",
    "gn:asciiname":"Trinidad",
    "gn:country_code":"BZ",
    "gn:dem":20,
    "gn:feature_class":"P",
    "gn:feature_code":"PPL",
    "gn:name":"Trinidad",
    "gn:population":0,
    "gn:timezone":"America/Belize",
    "iso:country":"BZ",
    "wof:name":"Trinidad",
    "wof:placetype":"locality"
},
  "geometry": {"coordinates":[-88.68698000000001,18.02356],"type":"Point"}
}