{
  "type": "Feature",
  "properties": {
    "gn:admin1_code":"2.0",
    "gn:asciiname":"More Tomorrow",
    "gn:country_code":"BZ",
    "gn:dem":31,
    "gn:feature_class":"P",
    "gn:feature_code":"PPL",
    "gn:name":"More Tomorrow",
    "gn:population":0,
    "gn:timezone":"America/Belize",
    "iso:country":"BZ",
    "wof:name":"More Tomorrow",
    "wof:placetype":"locality"
},
  "geometry": {"coordinates":[-88.69204000000001,17.34734],"type":"Point"}
}