{
  "type": "Feature",
  "properties": {
    "gn:admin1_code":"1.0",
    "gn:asciiname":"Rancho Dolores",
    "gn:country_code":"BZ",
    "gn:dem":21,
    "gn:feature_class":"P",
    "gn:feature_code":"PPL",
    "gn:name":"Rancho Dolores",
    "gn:population":0,
    "gn:timezone":"America/Belize",
    "iso:country":"BZ",
    "name:und_x_variant":[
        "Dolores",
        "Rancho Dolores"
    ],
    "wof:name":"Rancho Dolores",
    "wof:placetype":"locality"
},
  "geometry": {"coordinates":[-88.6285,17.53569],"type":"Point"}
}