{
  "type": "Feature",
  "properties": {
    "gn:admin1_code":"4.0",
    "gn:asciiname":"Ramonal",
    "gn:country_code":"BZ",
    "gn:dem":223,
    "gn:feature_class":"P",
    "gn:feature_code":"PPL",
    "gn:name":"Ramonal",
    "gn:population":0,
    "gn:timezone":"America/Belize",
    "iso:country":"BZ",
    "wof:name":"Ramonal",
    "wof:placetype":"locality"
},
  "geometry": {"coordinates":[-89.13240999999999,17.41183],"type":"Point"}
}