{
  "type": "Feature",
  "properties": {
    "gn:admin1_code":"6.0",
    "gn:asciiname":"San Pedro Landing",
    "gn:country_code":"BZ",
    "gn:dem":11,
    "gn:feature_class":"P",
    "gn:feature_code":"PPL",
    "gn:name":"San Pedro Landing",
    "gn:population":0,
    "gn:timezone":"America/Belize",
    "iso:country":"BZ",
    "name:und_x_variant":[
        "San Pedro",
        "San Pedro Landing"
    ],
    "wof:name":"San Pedro Landing",
    "wof:placetype":"locality"
},
  "geometry": {"coordinates":[-89.20444000000001,15.93768],"type":"Point"}
}