{
  "type": "Feature",
  "properties": {
    "gn:admin1_code":"2.0",
    "gn:asciiname":"Negroman",
    "gn:country_code":"BZ",
    "gn:dem":81,
    "gn:feature_class":"P",
    "gn:feature_code":"PPL",
    "gn:name":"Negroman",
    "gn:population":0,
    "gn:timezone":"America/Belize",
    "iso:country":"BZ",
    "wof:name":"Negroman",
    "wof:placetype":"locality"
},
  "geometry": {"coordinates":[-89.08331,17.07844],"type":"Point"}
}