{
  "type": "Feature",
  "properties": {
    "gn:admin1_code":"2.0",
    "gn:asciiname":"Blackman Eddy",
    "gn:country_code":"BZ",
    "gn:dem":91,
    "gn:feature_class":"P",
    "gn:feature_code":"PPL",
    "gn:name":"Blackman Eddy",
    "gn:population":0,
    "gn:timezone":"America/Belize",
    "iso:country":"BZ",
    "wof:name":"Blackman Eddy",
    "wof:placetype":"locality"
},
  "geometry": {"coordinates":[-88.91670000000001,17.2167],"type":"Point"}
}