{
  "type": "Feature",
  "properties": {
    "gn:admin1_code":"1.0",
    "gn:asciiname":"Sand Hill",
    "gn:country_code":"BZ",
    "gn:dem":12,
    "gn:feature_class":"P",
    "gn:feature_code":"PPL",
    "gn:name":"Sand Hill",
    "gn:population":0,
    "gn:timezone":"America/Belize",
    "iso:country":"BZ",
    "name:nds_x_preferred":[
        "Sand Hill"
    ],
    "wof:name":"Sand Hill",
    "wof:placetype":"locality"
},
  "geometry": {"coordinates":[-88.36828,17.64038],"type":"Point"}
}