{
  "type": "Feature",
  "properties": {
    "gn:admin1_code":"1.0",
    "gn:asciiname":"Revenge",
    "gn:country_code":"BZ",
    "gn:dem":12,
    "gn:feature_class":"P",
    "gn:feature_code":"PPL",
    "gn:name":"Revenge",
    "gn:population":0,
    "gn:timezone":"America/Belize",
    "iso:country":"BZ",
    "name:ara_x_preferred":[
        "\u0627\u0646\u062a\u0642\u0627\u0645"
    ],
    "name:arz_x_preferred":[
        "\u062a\u0627\u0631"
    ],
    "name:bel_x_preferred":[
        "\u041f\u043e\u043c\u0441\u0442\u0430"
    ],
    "name:bre_x_preferred":[
        "Dial"
    ],
    "name:bul_x_preferred":[
        "\u041e\u0442\u043c\u044a\u0449\u0435\u043d\u0438\u0435"
    ],
    "name:cat_x_preferred":[
        "Venjan\u00e7a"
    ],
    "name:dan_x_preferred":[
        "H\u00e6vn"
    ],
    "name:deu_x_preferred":[
        "Rache"
    ],
    "name:epo_x_preferred":[
        "Ven\u011do"
    ],
    "name:est_x_preferred":[
        "K\u00e4ttemaks"
    ],
    "name:eus_x_preferred":[
        "Mendeku"
    ],
    "name:fas_x_preferred":[
        "\u0627\u0646\u062a\u0642\u0627\u0645"
    ],
    "name:fin_x_preferred":[
        "Kosto"
    ],
    "name:fra_x_preferred":[
        "Vengeance"
    ],
    "name:fry_x_preferred":[
        "Wraak"
    ],
    "name:glg_x_preferred":[
        "Vinganza"
    ],
    "name:heb_x_preferred":[
        "\u05e0\u05e7\u05de\u05d4"
    ],
    "name:hin_x_preferred":[
        "\u092a\u094d\u0930\u0924\u093f\u0936\u094b\u0927"
    ],
    "name:hrv_x_preferred":[
        "Osveta"
    ],
    "name:ita_x_preferred":[
        "Vendetta"
    ],
    "name:kan_x_preferred":[
        "\u0cb8\u0cc7\u0ca1\u0cc1"
    ],
    "name:msa_x_preferred":[
        "Dendam"
    ],
    "name:nld_x_preferred":[
        "Wraak"
    ],
    "name:nno_x_preferred":[
        "Hemn"
    ],
    "name:nor_x_preferred":[
        "Hevn"
    ],
    "name:pol_x_preferred":[
        "Zemsta"
    ],
    "name:por_x_preferred":[
        "Vendeta"
    ],
    "name:rus_x_preferred":[
        "\u041c\u0435\u0441\u0442\u044c"
    ],
    "name:spa_x_preferred":[
        "Venganza"
    ],
    "name:swe_x_preferred":[
        "H\u00e4mnd"
    ],
    "name:tam_x_preferred":[
        "\u0baa\u0bb4\u0bbf\u0bb5\u0bbe\u0b99\u0bcd\u0b95\u0bc1\u0ba4\u0bb2\u0bcd"
    ],
    "name:tgl_x_preferred":[
        "Paghihiganti"
    ],
    "name:tur_x_preferred":[
        "\u0130ntikam"
    ],
    "name:ukr_x_preferred":[
        "\u041f\u043e\u043c\u0441\u0442\u0430"
    ],
    "name:uzb_x_preferred":[
        "Vendetta"
    ],
    "wof:name":"Revenge",
    "wof:placetype":"locality"
},
  "geometry": {"coordinates":[-88.55164000000001,17.86254],"type":"Point"}
}