{
  "type": "Feature",
  "properties": {
    "gn:admin1_code":"1.0",
    "gn:asciiname":"Revenge",
    "gn:country_code":"BZ",
    "gn:dem":12,
    "gn:feature_class":"P",
    "gn:feature_code":"PPL",
    "gn:name":"Revenge",
    "gn:population":0,
    "gn:timezone":"America/Belize",
    "iso:country":"BZ",
    "wof:name":"Revenge",
    "wof:placetype":"locality"
},
  "geometry": {"coordinates":[-88.55164000000001,17.86254],"type":"Point"}
}