{
  "type": "Feature",
  "properties": {
    "gn:admin1_code":"4.0",
    "gn:asciiname":"San Juan Bank",
    "gn:country_code":"BZ",
    "gn:dem":19,
    "gn:feature_class":"P",
    "gn:feature_code":"PPL",
    "gn:name":"San Juan Bank",
    "gn:population":0,
    "gn:timezone":"America/Belize",
    "iso:country":"BZ",
    "wof:name":"San Juan Bank",
    "wof:placetype":"locality"
},
  "geometry": {"coordinates":[-88.30011,17.98595],"type":"Point"}
}