{
  "type": "Feature",
  "properties": {
    "gn:admin1_code":"2.0",
    "gn:asciiname":"Cool Shade",
    "gn:country_code":"BZ",
    "gn:dem":107,
    "gn:feature_class":"P",
    "gn:feature_code":"PPL",
    "gn:name":"Cool Shade",
    "gn:population":0,
    "gn:timezone":"America/Belize",
    "iso:country":"BZ",
    "wof:name":"Cool Shade",
    "wof:placetype":"locality"
},
  "geometry": {"coordinates":[-88.96788000000002,17.17137],"type":"Point"}
}