{
  "type": "Feature",
  "properties": {
    "gn:admin1_code":"5.0",
    "gn:asciiname":"Dancing Pool",
    "gn:country_code":"BZ",
    "gn:dem":51,
    "gn:feature_class":"P",
    "gn:feature_code":"PPL",
    "gn:name":"Dancing Pool",
    "gn:population":0,
    "gn:timezone":"America/Belize",
    "iso:country":"BZ",
    "wof:name":"Dancing Pool",
    "wof:placetype":"locality"
},
  "geometry": {"coordinates":[-88.43737,16.83119],"type":"Point"}
}