{
  "type": "Feature",
  "properties": {
    "gn:admin1_code":"3.0",
    "gn:asciiname":"Aventura",
    "gn:country_code":"BZ",
    "gn:dem":11,
    "gn:feature_class":"P",
    "gn:feature_code":"PPL",
    "gn:name":"Aventura",
    "gn:population":0,
    "gn:timezone":"America/Belize",
    "iso:country":"BZ",
    "wof:name":"Aventura",
    "wof:placetype":"locality"
},
  "geometry": {"coordinates":[-88.44884999999999,18.33012],"type":"Point"}
}