{
  "type": "Feature",
  "properties": {
    "gn:admin1_code":"2.0",
    "gn:asciiname":"Bullet Tree Falls",
    "gn:country_code":"BZ",
    "gn:dem":69,
    "gn:feature_class":"P",
    "gn:feature_code":"PPL",
    "gn:name":"Bullet Tree Falls",
    "gn:population":0,
    "gn:timezone":"America/Belize",
    "iso:country":"BZ",
    "wof:name":"Bullet Tree Falls",
    "wof:placetype":"locality"
},
  "geometry": {"coordinates":[-89.111,17.168],"type":"Point"}
}