{
  "type": "Feature",
  "properties": {
    "gn:admin1_code":"3.0",
    "gn:asciiname":"San Roman",
    "gn:country_code":"BZ",
    "gn:dem":8,
    "gn:feature_class":"P",
    "gn:feature_code":"PPL",
    "gn:name":"San Roman",
    "gn:population":0,
    "gn:timezone":"America/Belize",
    "iso:country":"BZ",
    "wof:name":"San Roman",
    "wof:placetype":"locality"
},
  "geometry": {"coordinates":[-88.50775,18.2972],"type":"Point"}
}