{
  "type": "Feature",
  "properties": {
    "gn:admin1_code":"6.0",
    "gn:asciiname":"Sunday Wood Creek Village",
    "gn:country_code":"BZ",
    "gn:dem":27,
    "gn:feature_class":"P",
    "gn:feature_code":"PPL",
    "gn:name":"Sunday Wood Creek Village",
    "gn:population":0,
    "gn:timezone":"America/Belize",
    "iso:country":"BZ",
    "name:spa_x_preferred":[
        "Sunday Wood Creek Village"
    ],
    "wof:name":"Sunday Wood Creek Village",
    "wof:placetype":"locality"
},
  "geometry": {"coordinates":[-89.02868000000002,16.0391],"type":"Point"}
}