{
  "type": "Feature",
  "properties": {
    "gn:admin1_code":"1.0",
    "gn:asciiname":"Caye Caulker",
    "gn:country_code":"BZ",
    "gn:dem":5,
    "gn:feature_class":"P",
    "gn:feature_code":"PPL",
    "gn:name":"Caye Caulker",
    "gn:population":0,
    "gn:timezone":"America/Belize",
    "iso:country":"BZ",
    "name:eng_x_preferred":[
        "Caye Caulker"
    ],
    "name:fra_x_preferred":[
        "Caye Caulker"
    ],
    "name:spa_x_preferred":[
        "Cayo Corker"
    ],
    "wof:name":"Caye Caulker",
    "wof:placetype":"locality"
},
  "geometry": {"coordinates":[-88.02761,17.73659],"type":"Point"}
}