{
  "type": "Feature",
  "properties": {
    "gn:admin1_code":"1.0",
    "gn:asciiname":"Caye Caulker",
    "gn:country_code":"BZ",
    "gn:dem":5,
    "gn:feature_class":"P",
    "gn:feature_code":"PPL",
    "gn:name":"Caye Caulker",
    "gn:population":0,
    "gn:timezone":"America/Belize",
    "iso:country":"BZ",
    "name:ara_x_preferred":[
        "\u0643\u0627\u064a \u0643\u0648\u0644\u0643\u0631"
    ],
    "name:ceb_x_preferred":[
        "Cay Corker"
    ],
    "name:deu_x_preferred":[
        "Caye Caulker"
    ],
    "name:eng_x_preferred":[
        "Caye Caulker"
    ],
    "name:fra_x_preferred":[
        "Caye Caulker"
    ],
    "name:hrv_x_preferred":[
        "Caye Caulker"
    ],
    "name:lit_x_preferred":[
        "Kolkerio Sala"
    ],
    "name:nds_x_preferred":[
        "Caye Caulker"
    ],
    "name:nld_x_preferred":[
        "Caye Caulker"
    ],
    "name:nor_x_preferred":[
        "Caye Caulker"
    ],
    "name:pol_x_preferred":[
        "Caye Caulker"
    ],
    "name:por_x_preferred":[
        "Caye Caulker"
    ],
    "name:spa_x_preferred":[
        "Cayo Corker"
    ],
    "name:swe_x_preferred":[
        "Caye Caulker"
    ],
    "wof:name":"Caye Caulker",
    "wof:placetype":"locality"
},
  "geometry": {"coordinates":[-88.02761,17.73659],"type":"Point"}
}