{
  "type": "Feature",
  "properties": {
    "gn:admin1_code":"2.0",
    "gn:asciiname":"Panama",
    "gn:country_code":"BZ",
    "gn:dem":29,
    "gn:feature_class":"P",
    "gn:feature_code":"PPL",
    "gn:name":"Panama",
    "gn:population":0,
    "gn:timezone":"America/Belize",
    "iso:country":"BZ",
    "wof:name":"Panama",
    "wof:placetype":"locality"
},
  "geometry": {"coordinates":[-88.69183000000002,17.35458],"type":"Point"}
}