{
  "type": "Feature",
  "properties": {
    "gn:admin1_code":"3.0",
    "gn:asciiname":"Estero",
    "gn:country_code":"BZ",
    "gn:dem":7,
    "gn:feature_class":"P",
    "gn:feature_code":"PPL",
    "gn:name":"Estero",
    "gn:population":0,
    "gn:timezone":"America/Belize",
    "iso:country":"BZ",
    "wof:name":"Estero",
    "wof:placetype":"locality"
},
  "geometry": {"coordinates":[-88.50239000000001,18.41252],"type":"Point"}
}