{
  "type": "Feature",
  "properties": {
    "iso:country":"BZ",
    "ne:ADM0CAP":0.0,
    "ne:ADM0NAME":"Belize",
    "ne:ADM0_A3":"BLZ",
    "ne:ADM1NAME":"Cayo",
    "ne:ADMIN1_COD":0,
    "ne:CAPALT":0,
    "ne:CHANGED":4,
    "ne:CHECKME":0,
    "ne:COMPARE":0,
    "ne:DIFFASCII":0,
    "ne:DIFFNOTE":"Added missing admin-1 capital.",
    "ne:ELEVATION":0.0,
    "ne:FEATURECLA":"Admin-1 capital",
    "ne:GEONAMEID":-1,
    "ne:GN_POP":0,
    "ne:GTOPO30":0.0,
    "ne:ISO_A2":"BZ",
    "ne:LABELRANK":8,
    "ne:LATITUDE":17.155998,
    "ne:LONGITUDE":-89.061003,
    "ne:LS_MATCH":0,
    "ne:MAX_AREAKM":0.0,
    "ne:MAX_AREAMI":0.0,
    "ne:MAX_BBXMAX":0.0,
    "ne:MAX_BBXMIN":0.0,
    "ne:MAX_BBYMAX":0.0,
    "ne:MAX_BBYMIN":0.0,
    "ne:MAX_NATSCA":0.0,
    "ne:MAX_PERKM":0.0,
    "ne:MAX_PERMI":0.0,
    "ne:MAX_POP10":0,
    "ne:MAX_POP20":0,
    "ne:MAX_POP300":0,
    "ne:MAX_POP310":0,
    "ne:MAX_POP50":0,
    "ne:MEAN_BBXC":0.0,
    "ne:MEAN_BBYC":0.0,
    "ne:MEGACITY":0,
    "ne:MIN_AREAKM":0.0,
    "ne:MIN_AREAMI":0.0,
    "ne:MIN_BBXMAX":0.0,
    "ne:MIN_BBXMIN":0.0,
    "ne:MIN_BBYMAX":0.0,
    "ne:MIN_BBYMIN":0.0,
    "ne:MIN_PERKM":0.0,
    "ne:MIN_PERMI":0.0,
    "ne:NAME":"El Cayo",
    "ne:NAMEASCII":"El Cayo",
    "ne:NAMEDIFF":1,
    "ne:NATSCALE":5,
    "ne:POP1950":0,
    "ne:POP1955":0,
    "ne:POP1960":0,
    "ne:POP1965":0,
    "ne:POP1970":0,
    "ne:POP1975":0,
    "ne:POP1980":0,
    "ne:POP1985":0,
    "ne:POP1990":0,
    "ne:POP1995":0,
    "ne:POP2000":0,
    "ne:POP2005":0,
    "ne:POP2010":0,
    "ne:POP2015":0,
    "ne:POP2020":0,
    "ne:POP2025":0,
    "ne:POP2050":0,
    "ne:POP_MAX":16977,
    "ne:POP_MIN":9925,
    "ne:POP_OTHER":0,
    "ne:RANK_MAX":6,
    "ne:RANK_MIN":5,
    "ne:SCALERANK":9,
    "ne:SOV0NAME":"Belize",
    "ne:SOV_A3":"BLZ",
    "ne:UN_FID":0,
    "ne:UN_LAT":0.0,
    "ne:UN_LONG":0.0,
    "ne:WORLDCITY":0,
    "ne:min_zoom":7.0,
    "wof:name":"El Cayo",
    "wof:placetype":"locality"
},
  "geometry": {"coordinates":[-89.06100252218641,17.15599807453884],"type":"Point"}
}