{
  "type": "Feature",
  "properties": {
    "iso:country":"BZ",
    "name:eng_x_preferred":[
        "The Big Fall"
    ],
    "qs:gn_country":"BZ",
    "qs:gn_fcode":"PPL",
    "qs:gn_pop":0,
    "qs:name":"Big Fall",
    "qs:name_adm0":"Belize",
    "qs:name_adm1":"Toledo",
    "qs:photos":223,
    "qs:photos_1k":45,
    "qs:photos_9k":1,
    "qs:photos_9r":4,
    "qs:photos_all":223,
    "qs:photos_sr":4,
    "qs:placetype":"Town",
    "qs:pop_sr":"0",
    "qs:woe_adm0":23424760,
    "wd:wordcount":65,
    "wof:name":"Big Fall",
    "wof:placetype":"locality"
},
  "geometry": {"coordinates":[-88.88333,16.25],"type":"Point"}
}